<?xml version="1.0" encoding="UTF-8"?>
<!--  This file conforms to the DTD xdc/bld/build.dtd -->
<package name="ti.ipc" version="1, 0, 0, 0" producerId="undefined">
    <units>
    </units>
    <sources>
    </sources>
    <configscripts>
    </configscripts>
    <makefiles>
        <srcFile name="package.mak" src="package.bld"/>
        <srcFile name="package/package.xdc.dep" src="package.xdc"/>
        <srcFile name="package/package.cfg.dep" src="package.xdc"/>
        <srcFile name="package/rel/ti_ipc.tar.gz.dep" src="package/rel/ti_ipc.xdc.inc"/>
    </makefiles>
    <targets>
    </targets>
    <libraries>
    </libraries>
    <configurations>
    </configurations>
    <executables>
    </executables>
    <tests>
    </tests>
    <releases relDir="package/rel/">
    <release name="ti_ipc"
        pname="ti_ipc.tar.gz"
        label="default"
    >
        <file name="package/package.bld.xml"/>
        <file name="package/build.cfg"/>
        <file name="package/package.xdc.inc"/>
        <file name="GateMP.h"/>
        <file name="HeapBufMP.h"/>
        <file name="HeapMemMP.h"/>
        <file name="HeapMultiBufMP.h"/>
        <file name="Ipc.h"/>
        <file name="ListMP.h"/>
        <file name="MessageQ.h"/>
        <file name="MultiProc.h"/>
        <file name="NameServer.h"/>
        <file name="Notify.h"/>
        <file name="SharedRegion.h"/>
        <file name="package.bld"/>
        <file name="package/package.cfg.xdc.inc"/>
    </release>
    </releases>
    <repositories>
    </repositories>
</package>
